pyqt_svg_abstractbutton/__init__.py
pyqt_svg_abstractbutton/svgAbstractButton.py
pyqt_svg_abstractbutton-0.0.7.dist-info/LICENSE
pyqt_svg_abstractbutton-0.0.7.dist-info/METADATA
pyqt_svg_abstractbutton-0.0.7.dist-info/WHEEL
pyqt_svg_abstractbutton-0.0.7.dist-info/top_level.txt
pyqt_svg_abstractbutton-0.0.7.dist-info/RECORD
