Metadata-Version: 2.1
Name: pyqt-svg-abstractbutton
Version: 0.0.7
Summary: PyQt QAbstractButton for pyqt-svg-button and pyqt-svg-toolbutton
Home-page: https://github.com/yjg30737/pyqt-svg-abstractbutton.git
Author: Jung Gyu Yoon
Author-email: yjg30737@gmail.com
License: MIT
Platform: UNKNOWN
License-File: LICENSE
Requires-Dist: PyQt5 (>=5.8)
